weasel_client/__init__.py
weasel_client/__version__.py
weasel_client/api_client.py
weasel_client/connection_manager.py
weasel_client/exceptions.py
weasel_client/raw_results/__init__.py
weasel_client/raw_results/fetcher.py
weasel_client/resources/__init__.py
weasel_client/resources/date_statistics.py
weasel_client/resources/release.py
weasel_client/resources/release_counter.py
weasel_client/resources/release_sourcefile.py
weasel_client/resources/resource.py
weasel_client/resources/sourcefile.py
weasel_client/resources/technology.py
weasel_client/resources/vulnerability.py
weasel_client/scripts/__init__.py
weasel_client/scripts/raw_result_fetcher.py
weasel_client-0.0.9.dist-info/entry_points.txt
weasel_client-0.0.9.dist-info/WHEEL
weasel_client-0.0.9.dist-info/METADATA
weasel_client-0.0.9.dist-info/RECORD
