Metadata-Version: 2.1
Name: weasel-client
Version: 0.0.9
Summary: `weasel-client` is a python library to access the `weasel-api`.
Author: Lennart Haas
Author-email: haasl@cs.uni-bonn.de
Requires-Python: >=3.7,<4.0
Classifier: Programming Language :: Python :: 3
Classifier: Programming Language :: Python :: 3.7
Classifier: Programming Language :: Python :: 3.8
Classifier: Programming Language :: Python :: 3.9
Requires-Dist: python-dateutil (>=2.8.1,<3.0.0)
Requires-Dist: requests (>=2.25.1,<3.0.0)
